{"name":"build-javascript","namedChunkGroups":{"polyfill":{"name":"polyfill","assets":[{"name":"webpack-runtime-9ef8b5787d0b7aabaae3.js","size":5087},{"name":"polyfill-5f5bcb5f203e7eaa426a.js","size":85848}],"filteredAssets":0,"assetsSize":90935,"filteredAuxiliaryAssets":2,"auxiliaryAssetsSize":228337},"app":{"name":"app","assets":[{"name":"webpack-runtime-9ef8b5787d0b7aabaae3.js","size":5087},{"name":"framework-975df2597b0bbbcc2868.js","size":130446},{"name":"app-7c2a24132114b7971747.js","size":103944}],"filteredAssets":0,"assetsSize":239477,"filteredAuxiliaryAssets":3,"auxiliaryAssetsSize":773871},"component---src-pages-404-js":{"name":"component---src-pages-404-js","assets":[{"name":"component---src-pages-404-js-946747276dbeff201e4a.js","size":812}],"filteredAssets":0,"assetsSize":812,"filteredAuxiliaryAssets":1,"auxiliaryAssetsSize":1981},"component---src-pages-index-tsx":{"name":"component---src-pages-index-tsx","assets":[{"name":"framework-975df2597b0bbbcc2868.js","size":130446},{"name":"styles.3a78e4a2adff24dfb119.css","size":69830},{"name":"component---src-pages-index-tsx-706b6d1c3b6c48837946.js","size":136600}],"filteredAssets":0,"assetsSize":336876,"filteredAuxiliaryAssets":6,"auxiliaryAssetsSize":1094057}},"assetsByChunkName":{"polyfill":["webpack-runtime-9ef8b5787d0b7aabaae3.js","polyfill-5f5bcb5f203e7eaa426a.js"],"app":["webpack-runtime-9ef8b5787d0b7aabaae3.js","framework-975df2597b0bbbcc2868.js","app-7c2a24132114b7971747.js"],"component---src-pages-404-js":["component---src-pages-404-js-946747276dbeff201e4a.js"],"component---src-pages-index-tsx":["framework-975df2597b0bbbcc2868.js","styles.3a78e4a2adff24dfb119.css","component---src-pages-index-tsx-706b6d1c3b6c48837946.js"]},"childAssetsByChunkName":{}}